pyscheme/__init__.py
pyscheme/atoms.py
pyscheme/core.py
pyscheme/parse.py
pyscheme/parse_algebra.py
pyscheme/parse_scheme.py
pyscheme/special_forms.py
pyscheme/typing.py
pyscheme/test/__init__.py
pyscheme/test/test_core.py
pyscheme/test/test_package.py
pyscheme/test/test_parse_algebra.py
pyscheme/test/test_parse_scheme.py
pyscheme/test/test_special_forms.py
startables/__init__.py
startables/startables.py
startables/units.py
startables/readers/__init__.py
startables/readers/bulk.py
startables/readers/word.py
startables-0.8.5.dist-info/LICENSE.txt
startables-0.8.5.dist-info/METADATA
startables-0.8.5.dist-info/WHEEL
startables-0.8.5.dist-info/top_level.txt
startables-0.8.5.dist-info/RECORD
