Metadata-Version: 2.1
Name: startables
Version: 0.8.5
Summary: Reads, writes, and manipulates data stored in StarTable format
Home-page: https://github.com/startable/startables-python/
Author: Jean-François Corbett
Author-email: jeaco@orsted.dk
License: BSD-3-Clause
Keywords: startable data-structure file-format table
Platform: UNKNOWN
Classifier: Development Status :: 4 - Beta
Classifier: Intended Audience :: Developers
Classifier: License :: OSI Approved :: BSD License
Classifier: Programming Language :: Python :: 3
Requires-Python: >=3.6
Requires-Dist: numpy
Requires-Dist: pandas
Requires-Dist: openpyxl
